femagroundmotions/__init__.py
femagroundmotions/__version__
femagroundmotions/atcparse.py
femagroundmotions/hdf5.py
femagroundmotions/spectra.py
femagroundmotions-2.0.0.dist-info/LICENSE
femagroundmotions-2.0.0.dist-info/METADATA
femagroundmotions-2.0.0.dist-info/WHEEL
femagroundmotions-2.0.0.dist-info/top_level.txt
femagroundmotions-2.0.0.dist-info/RECORD
