Metadata-Version: 2.1
Name: femagroundmotions
Version: 2.0.0
Summary: FEMA P695 ground motion data in multiple formats.
Home-page: https://github.com/otaithleigh/fema-ground-motions
Author: Peter Talley
Author-email: peterctalley@gmail.com
License: MIT
Platform: UNKNOWN
Requires-Python: >=3.7
Requires-Dist: h5py
Requires-Dist: hdf5plugin
Requires-Dist: openpyxl
Requires-Dist: opswrapper
Requires-Dist: pandas
Requires-Dist: tables
Requires-Dist: xarray
